{"rows":9,"cols":13,"teleporters":[],"switches":[{"col":0,"row":6,"enabled":[{"col":2,"row":5,"visible":true},{"col":3,"row":0,"visible":true},{"col":4,"row":0,"visible":true},{"col":5,"row":0,"visible":true},{"col":6,"row":0,"visible":true},{"col":3,"row":1,"visible":true},{"col":3,"row":2,"visible":true},{"col":5,"row":1,"visible":true},{"col":5,"row":2,"visible":true}],"disabled":[{"col":2,"row":5,"visible":false},{"col":3,"row":0,"visible":false},{"col":4,"row":0,"visible":false},{"col":5,"row":0,"visible":false},{"col":6,"row":0,"visible":false},{"col":3,"row":1,"visible":false},{"col":3,"row":2,"visible":false},{"col":5,"row":1,"visible":false},{"col":5,"row":2,"visible":false}]},{"col":3,"row":3,"enabled":[{"col":10,"row":4,"visible":true},{"col":11,"row":4,"visible":true}],"disabled":[{"col":10,"row":4,"visible":false},{"col":11,"row":4,"visible":false}]}],"hint":"https://www.youtube.com/watch?v=EaTNvNmfhJg"}